{
    "variants": {
        "variant=sacred_oak": { "model": "biomesoplenty:sacred_oak_planks" },
        "variant=cherry": { "model": "biomesoplenty:cherry_planks" },
        "variant=umbran": { "model": "biomesoplenty:umbran_planks" },
        "variant=fir": { "model": "biomesoplenty:fir_planks" },
        "variant=ethereal": { "model": "biomesoplenty:ethereal_planks" },
        "variant=magic": { "model": "biomesoplenty:magic_planks" },
        "variant=mangrove": { "model": "biomesoplenty:mangrove_planks" },
        "variant=palm": { "model": "biomesoplenty:palm_planks" }
    }
}