{
	"replace": false,
	"values": [
        {
            "id": "biomesoplenty:crag",
            "required": false
        },
        {
            "id": "biomesoplenty:highland",
            "required": false
        },
        {
            "id": "biomesoplenty:jade_cliffs",
            "required": false
        },
        {
            "id": "biomesoplenty:moor",
            "required": false
        },
        {
            "id": "biomesoplenty:volcano",
            "required": false
        }
	]
}