{
	"ambientocclusion": false,
	"textures": {
		"outer": "biomesoplenty:block/waterlily_outer",
		"inner": "biomesoplenty:block/waterlily_inner",
		"stem": "biomesoplenty:block/waterlily_stem",
		"particle": "#outer"
	},
	"elements": [
		{
			"from": [7.4, -1.5, 0],
			"to": [23.4, -1.5, 16],
			"shade": false,
			"rotation": {"angle": 22.5, "axis": "z", "origin": [8, 0, 0]},
			"faces": {
				"up": {"uv": [0, 0, 16, 16], "rotation": 90, "texture": "#outer"},
				"down": {"uv": [0, 16, 16, 0], "rotation": 270, "texture": "#outer"}
			}
		},
		{
			"from": [-7.4, -1.5, 0],
			"to": [8.6, -1.5, 16],
			"shade": false,
			"rotation": {"angle": -22.5, "axis": "z", "origin": [8, 0, 0]},
			"faces": {
				"up": {"uv": [0, 0, 16, 16], "rotation": 270, "texture": "#outer"},
				"down": {"uv": [0, 16, 16, 0], "rotation": 90, "texture": "#outer"}
			}
		},
		{
			"from": [0, -1.5, 7.4],
			"to": [16, -1.5, 23.4],
			"shade": false,
			"rotation": {"angle": -22.5, "axis": "x", "origin": [0, 0, 8]},
			"faces": {
				"up": {"uv": [16, 16, 0, 0], "texture": "#outer"},
				"down": {"uv": [16, 0, 0, 16], "texture": "#outer"}
			}
		},
		{
			"from": [0, -1.5, -7.4],
			"to": [16, -1.5, 8.6],
			"shade": false,
			"rotation": {"angle": 22.5, "axis": "x", "origin": [0, 0, 8]},
			"faces": {
				"up": {"uv": [0, 0, 16, 16], "texture": "#outer"},
				"down": {"uv": [0, 16, 16, 0], "texture": "#outer"}
			}
		},
		{
			"from": [8.6, -1.5, 0],
			"to": [8.6, 14.5, 16],
			"shade": false,
			"rotation": {"angle": -22.5, "axis": "z", "origin": [8, 0, 0]},
			"faces": {
				"east": {"uv": [0, 16, 16, 0], "rotation": 180, "texture": "#inner"},
				"west": {"uv": [0, 0, 16, 16], "texture": "#inner"}
			}
		},
		{
			"from": [7.4, -1.5, 0],
			"to": [7.4, 14.5, 16],
			"shade": false,
			"rotation": {"angle": 22.5, "axis": "z", "origin": [8, 0, 0]},
			"faces": {
				"east": {"uv": [0, 0, 16, 16], "texture": "#inner"},
				"west": {"uv": [0, 16, 16, 0], "rotation": 180, "texture": "#inner"}
			}
		},
		{
			"from": [0, -1.5, 8.6],
			"to": [16, 14.5, 8.6],
			"shade": false,
			"rotation": {"angle": 22.5, "axis": "x", "origin": [0, 0, 8]},
			"faces": {
				"north": {"uv": [16, 16, 0, 0], "rotation": 180, "texture": "#inner"},
				"south": {"uv": [16, 0, 0, 16], "texture": "#inner"}
			}
		},
		{
			"from": [0, -1.5, 7.4],
			"to": [16, 14.5, 7.4],
			"shade": false,
			"rotation": {"angle": -22.5, "axis": "x", "origin": [0, 0, 8]},
			"faces": {
				"north": {"uv": [0, 16, 16, 0], "rotation": 180, "texture": "#inner"},
				"south": {"uv": [0, 0, 16, 16], "texture": "#inner"}
			}
		},
		{
			"from": [0.8, -14.6, 8],
			"to": [15.2, 1.4, 8],
			"shade": false,
			"rotation": {"angle": 45, "axis": "y", "origin": [8, 8, 8], "rescale": true},
			"faces": {
				"north": {"uv": [0, 0, 16, 16], "texture": "#stem"},
				"south": {"uv": [0, 0, 16, 16], "texture": "#stem"}
			}
		},
		{
			"from": [8, -14.6, 0.8],
			"to": [8, 1.4, 15.2],
			"shade": false,
			"rotation": {"angle": 45, "axis": "y", "origin": [8, 8, 8], "rescale": true},
			"faces": {
				"east": {"uv": [0, 0, 16, 16], "texture": "#stem"},
				"west": {"uv": [0, 0, 16, 16], "texture": "#stem"}
			}
		}
	]
}